microwave_controller/contador/timer/nivel3/counter10.v
module counter10(clk,rst,count);
  input clk,rst;

  output reg [3:0]count;

  always@(posedge clk)
begin
    if(rst == 1 || count == 9)
      count <= 0;
    else
      count <= count + 1;
  end
endmodule

microwave_controller/contador/timer/nivel3/counter10_tb.v
`include "counter10.v"

module tb_10();
  reg clk,rst;
  wire [3:0]count;
  counter10 c1(clk,rst,count);
  initial begin
    clk = 0;
    forever #5 clk = ~clk;
  end
  initial
  begin
    rst = 0;
    #5 rst = 1;
    #10 rst = 0;
    #200 $finish;
  end
  initial 
    $monitor("%d%d",clk,count);
  initial
  begin
    $dumpfile("counter10.vcd"); 
    $dumpvars;
  end
endmodule

microwave_controller/contador/timer/nivel3/counter10.vcd
$date
	Sat May 07 10:31:29 2022
$end
$version
	Icarus Verilog
$end
$timescale
	1s
$end
$scope module tb_10 $end
$var wire 4 ! count [3:0] $end
$var reg 1 " clk $end
$var reg 1 # rst $end
$scope module c1 $end
$var wire 1 " clk $end
$var wire 1 # rst $end
$var reg 4 $ count [3:0] $end
$upscope $end
$upscope $end
$enddefinitions $end
#0
$dumpvars
bx $
0#
0"
bx !
$end
#5
b0 !
b0 $
1#
1"
#10
0"
#15
b1 !
b1 $
1"
0#
#20
0"
#25
b10 !
b10 $
1"
#30
0"
#35
b11 !
b11 $
1"
#40
0"
#45
b100 !
b100 $
1"
#50
0"
#55
b101 !
b101 $
1"
#60
0"
#65
b110 !
b110 $
1"
#70
0"
#75
b111 !
b111 $
1"
#80
0"
#85
b1000 !
b1000 $
1"
#90
0"
#95
b1001 !
b1001 $
1"
#100
0"
#105
b0 !
b0 $
1"
#110
0"
#115
b1 !
b1 $
1"
#120
0"
#125
b10 !
b10 $
1"
#130
0"
#135
b11 !
b11 $
1"
#140
0"
#145
b100 !
b100 $
1"
#150
0"
#155
b101 !
b101 $
1"
#160
0"
#165
b110 !
b110 $
1"
#170
0"
#175
b111 !
b111 $
1"
#180
0"
#185
b1000 !
b1000 $
1"
#190
0"
#195
b1001 !
b1001 $
1"
#200
0"
#205
b0 !
b0 $
1"
#210
0"
#215
b1 !
b1 $
1"
