microwave_controller/contador/decodificador/decodificador.v
//decodificador de 7 segmentos
module  decodificador_hep (

//variáveis de input
    input wire [3:0] s_ones,
    input wire [3:0] s_tens,
    input wire [3:0] min,

//variáveis de output
    output wire [6:0] s_ones_segs ,
    output wire [6:0] s_tens_segs ,
    output wire [6:0] min_segs    
);
//atribuindo valores ao output
    assign s_ones_segs =(s_ones == 4'b0000)? 7'b1111110: 
                          (s_ones == 4'b0001)? 7'b0110000: 
                          (s_ones == 4'b0010)? 7'b1101101: 
                          (s_ones == 4'b0011)? 7'b1111001: 
                          (s_ones == 4'b0100)? 7'b0110011: 
                          (s_ones == 4'b0101)? 7'b1011011: 
                          (s_ones == 4'b0110)? 7'b1011111: 
                          (s_ones == 4'b0111)? 7'b1110000: 
                          (s_ones == 4'b1000)? 7'b1111111: 
                          (s_ones == 4'b1001)? 7'b1110011: 
                          8'bXXXX_XXXX ;


    assign s_tens_segs =(s_tens == 4'b0000)? 7'b1111110: 
                          (s_tens == 4'b0001)? 7'b0110000: 
                          (s_tens == 4'b0010)? 7'b1101101: 
                          (s_tens == 4'b0011)? 7'b1111001: 
                          (s_tens == 4'b0100)? 7'b0110011: 
                          (s_tens == 4'b0101)? 7'b1011011: 
                          (s_tens == 4'b0110)? 7'b1011111: 
                          (s_tens == 4'b0111)? 7'b1110000: 
                          (s_tens == 4'b1000)? 7'b1111111: 
                          (s_tens == 4'b1001)? 7'b1110011: 
                          8'bXXXX_XXXX ;


    assign min_segs =     (min == 4'b0000)? 7'b1111110: 
                          (min == 4'b0001)? 7'b0110000: 
                          (min == 4'b0010)? 7'b1101101: 
                          (min == 4'b0011)? 7'b1111001: 
                          (min == 4'b0100)? 7'b0110011: 
                          (min == 4'b0101)? 7'b1011011: 
                          (min == 4'b0110)? 7'b1011111: 
                          (min == 4'b0111)? 7'b1110000:
                          (min == 4'b1000)? 7'b1111111: 
                          (min == 4'b1001)? 7'b1110011: 
                          8'bXXXX_XXXX ; 
    
endmodule

microwave_controller/contador/decodificador/decodificador_tb.v
`timescale 1ns/1ps
`include "decodificador.v"

module decodificador_tb();

  reg [3:0] units_sec, tens_sec, minutes ;
  wire [6:0] minutes_segs , units_sec_segs , tens_sec_segs ;
  
  
/*
  module  decoder_hep (

//variáveis input
    input wire [3:0] sec_ones,
    input wire [3:0] sec_tens,
    input wire [3:0] min,

//variáveis output
    output wire [6:0] sec_ones_segs ,
    output wire [6:0] sec_tens_segs ,
    output wire [6:0] min_segs    
);
*/

// instancia o módulo dentro da bancada de teste.

  decodificador_hep DUT(
    .s_ones(units_sec), .s_tens(tens_sec), .min(minutes),
    .s_ones_segs(units_sec_segs) , .s_tens_segs(tens_sec_segs),
    .min_segs(minutes_segs)
  );
  initial
    begin
        
      $dumpfile("decodificador_tb.vcd");//Este arquivo conterá nossa simulação em forma de onda
      $dumpvars(0, decodificador_tb);
      
      // atribuir valores a nossas variáveis reg

      units_sec = 0; tens_sec = 0; minutes = 0;
      
      #10 units_sec = 1; tens_sec = 1; minutes = 0;
      #10 units_sec = 1; tens_sec = 1; minutes = 0;
      #10 units_sec = 1; tens_sec = 1; minutes = 0;
      #10 units_sec = 1; tens_sec = 1; minutes = 0;
      #10 units_sec = 1; tens_sec = 1; minutes = 1;
      #10 units_sec = 1; tens_sec = 1; minutes = 1;
      #10 units_sec = 1; tens_sec = 1; minutes = 1;
      #10 units_sec = 1; tens_sec = 1; minutes = 1;
      
      #10 units_sec = 1; tens_sec = 1; minutes = 0;
      #10 units_sec = 1; tens_sec = 1; minutes = 0;
      #10 units_sec = 1; tens_sec = 1; minutes = 0;
      #10 units_sec = 1; tens_sec = 1; minutes = 0;
      #10 units_sec = 1; tens_sec = 1; minutes = 1;
      #10 units_sec = 1; tens_sec = 1; minutes = 1;
      #10 units_sec = 1; tens_sec = 1; minutes = 1;
      #10 units_sec = 1; tens_sec = 1; minutes = 1;
      
      #10 units_sec = 1; tens_sec = 1; minutes = 1;
      #10 units_sec = 1; tens_sec = 1; minutes = 1;
      #10 units_sec = 1; tens_sec = 1; minutes = 1;
      #10 units_sec = 1; tens_sec = 1; minutes = 1;
      #10 units_sec = 1; tens_sec = 1; minutes = 1;
      #10 units_sec = 1; tens_sec = 0; minutes = 1;
      #10 units_sec = 1; tens_sec = 0; minutes = 1;
      #10 units_sec = 1; tens_sec = 0; minutes = 1;
      
      #10 units_sec = 0; tens_sec = 1; minutes = 1;
      #10 units_sec = 0; tens_sec = 1; minutes = 1;
      #10 units_sec = 0; tens_sec = 1; minutes = 1;
      #10 units_sec = 0; tens_sec = 1; minutes = 1;
      #10 units_sec = 0; tens_sec = 1; minutes = 1;
      #10 units_sec = 1; tens_sec = 1; minutes = 1;
      #10 units_sec = 1; tens_sec = 1; minutes = 1;
      #10 units_sec = 1; tens_sec = 1; minutes = 1;
      
      #10 units_sec = 1; tens_sec = 1; minutes = 1;
      #50 units_sec = 0; tens_sec = 1; minutes = 1;
      #5  units_sec = 1; tens_sec = 1; minutes = 1; 
      #50 units_sec = 1; tens_sec = 1; minutes = 1; 
      #50 units_sec = 1; tens_sec = 1; minutes = 1;  

    end

endmodule

microwave_controller/contador/decodificador/decodificador_tb.vcd
$date
	Sat May 07 10:48:14 2022
$end
$version
	Icarus Verilog
$end
$timescale
	1ps
$end
$scope module decodificador_tb $end
$var wire 7 ! units_sec_segs [6:0] $end
$var wire 7 " tens_sec_segs [6:0] $end
$var wire 7 # minutes_segs [6:0] $end
$var reg 4 $ minutes [3:0] $end
$var reg 4 % tens_sec [3:0] $end
$var reg 4 & units_sec [3:0] $end
$scope module DUT $end
$var wire 4 ' min [3:0] $end
$var wire 4 ( s_ones [3:0] $end
$var wire 4 ) s_tens [3:0] $end
$var wire 7 * s_tens_segs [6:0] $end
$var wire 7 + s_ones_segs [6:0] $end
$var wire 7 , min_segs [6:0] $end
$upscope $end
$upscope $end
$enddefinitions $end
#0
$dumpvars
b1111110 ,
b1111110 +
b1111110 *
b0 )
b0 (
b0 '
b0 &
b0 %
b0 $
b1111110 #
b1111110 "
b1111110 !
$end
#10000
b110000 "
b110000 *
b110000 !
b110000 +
b1 %
b1 )
b1 &
b1 (
#50000
b110000 #
b110000 ,
b1 $
b1 '
#90000
b1111110 #
b1111110 ,
b0 $
b0 '
#130000
b110000 #
b110000 ,
b1 $
b1 '
#220000
b1111110 "
b1111110 *
b0 %
b0 )
#250000
b110000 "
b110000 *
b1111110 !
b1111110 +
b1 %
b1 )
b0 &
b0 (
#300000
b110000 !
b110000 +
b1 &
b1 (
#380000
b1111110 !
b1111110 +
b0 &
b0 (
#385000
b110000 !
b110000 +
b1 &
b1 (
