microwave_controller/timer_input_control/debounce_delay.v
module debounce_delay(
    clock, clear,
    edge_out
);

    input clock, clear;
    output reg edge_out;

    reg [2:0] count;

    initial begin
        count <= 3'd7;
        edge_out <= 1'b0;
    end

    always @(posedge clock) begin
        if (clear == 1'b0) begin
            count <= 3'd0;
            edge_out <= 1'b0;
        end else begin
            if (count < 3'd7) begin
                count <= count + 3'd1;
            end else begin
                count <= 3'd7;
            end

            if (count == 3'd4) begin
                edge_out <= 1'b1;
            end
        end
    end

endmodule

microwave_controller/timer_input_control/testbenchs/debounce_delay_tb.v
`timescale 1ms/1ns
`include "..\debounce_delay.v"

module debounce_delay_tb;

    reg clock_tb, clear_tb;
    wire edge_out_tb;

    reg [7:0] counter_tb;

    debounce_delay uut(clock_tb, clear_tb, edge_out_tb);

    initial begin
        $dumpfile("../wave_forms/debounce_delay.vcd");
        $dumpvars(0, debounce_delay_tb);

        counter_tb = 8'd0;
        clock_tb = 1'b0;
        clear_tb = 1'b0;

        repeat(500) begin
            #5 clock_tb = ~clock_tb;
            counter_tb = counter_tb + 8'd1;

            if (counter_tb == 8'd10) begin
                clear_tb = 1'b1;
            end else if (counter_tb == 8'd100) begin
                clear_tb = 1'b0;    
            end
        end

    end

endmodule

microwave_controller/timer_input_control/wave_forms/debounce_delay.vcd
$date
	Sun May 01 19:10:53 2022
$end
$version
	Icarus Verilog
$end
$timescale
	1ns
$end
$scope module debounce_delay_tb $end
$var wire 1 ! edge_out_tb $end
$var reg 1 " clear_tb $end
$var reg 1 # clock_tb $end
$var reg 8 $ counter_tb [7:0] $end
$scope module uut $end
$var wire 1 " clear $end
$var wire 1 # clock $end
$var reg 3 % count [2:0] $end
$var reg 1 ! edge_out $end
$upscope $end
$upscope $end
$enddefinitions $end
#0
$dumpvars
b111 %
b0 $
0#
0"
0!
$end
#5000000
b0 %
b1 $
1#
#10000000
b10 $
0#
#15000000
b11 $
1#
#20000000
b100 $
0#
#25000000
b101 $
1#
#30000000
b110 $
0#
#35000000
b111 $
1#
#40000000
b1000 $
0#
#45000000
b1001 $
1#
#50000000
1"
b1010 $
0#
#55000000
b1 %
b1011 $
1#
#60000000
b1100 $
0#
#65000000
b10 %
b1101 $
1#
#70000000
b1110 $
0#
#75000000
b11 %
b1111 $
1#
#80000000
b10000 $
0#
#85000000
b100 %
b10001 $
1#
#90000000
b10010 $
0#
#95000000
1!
b101 %
b10011 $
1#
#100000000
b10100 $
0#
#105000000
b110 %
b10101 $
1#
#110000000
b10110 $
0#
#115000000
b111 %
b10111 $
1#
#120000000
b11000 $
0#
#125000000
b11001 $
1#
#130000000
b11010 $
0#
#135000000
b11011 $
1#
#140000000
b11100 $
0#
#145000000
b11101 $
1#
#150000000
b11110 $
0#
#155000000
b11111 $
1#
#160000000
b100000 $
0#
#165000000
b100001 $
1#
#170000000
b100010 $
0#
#175000000
b100011 $
1#
#180000000
b100100 $
0#
#185000000
b100101 $
1#
#190000000
b100110 $
0#
#195000000
b100111 $
1#
#200000000
b101000 $
0#
#205000000
b101001 $
1#
#210000000
b101010 $
0#
#215000000
b101011 $
1#
#220000000
b101100 $
0#
#225000000
b101101 $
1#
#230000000
b101110 $
0#
#235000000
b101111 $
1#
#240000000
b110000 $
0#
#245000000
b110001 $
1#
#250000000
b110010 $
0#
#255000000
b110011 $
1#
#260000000
b110100 $
0#
#265000000
b110101 $
1#
#270000000
b110110 $
0#
#275000000
b110111 $
1#
#280000000
b111000 $
0#
#285000000
b111001 $
1#
#290000000
b111010 $
0#
#295000000
b111011 $
1#
#300000000
b111100 $
0#
#305000000
b111101 $
1#
#310000000
b111110 $
0#
#315000000
b111111 $
1#
#320000000
b1000000 $
0#
#325000000
b1000001 $
1#
#330000000
b1000010 $
0#
#335000000
b1000011 $
1#
#340000000
b1000100 $
0#
#345000000
b1000101 $
1#
#350000000
b1000110 $
0#
#355000000
b1000111 $
1#
#360000000
b1001000 $
0#
#365000000
b1001001 $
1#
#370000000
b1001010 $
0#
#375000000
b1001011 $
1#
#380000000
b1001100 $
0#
#385000000
b1001101 $
1#
#390000000
b1001110 $
0#
#395000000
b1001111 $
1#
#400000000
b1010000 $
0#
#405000000
b1010001 $
1#
#410000000
b1010010 $
0#
#415000000
b1010011 $
1#
#420000000
b1010100 $
0#
#425000000
b1010101 $
1#
#430000000
b1010110 $
0#
#435000000
b1010111 $
1#
#440000000
b1011000 $
0#
#445000000
b1011001 $
1#
#450000000
b1011010 $
0#
#455000000
b1011011 $
1#
#460000000
b1011100 $
0#
#465000000
b1011101 $
1#
#470000000
b1011110 $
0#
#475000000
b1011111 $
1#
#480000000
b1100000 $
0#
#485000000
b1100001 $
1#
#490000000
b1100010 $
0#
#495000000
b1100011 $
1#
#500000000
0"
b1100100 $
0#
#505000000
0!
b0 %
b1100101 $
1#
#510000000
b1100110 $
0#
#515000000
b1100111 $
1#
#520000000
b1101000 $
0#
#525000000
b1101001 $
1#
#530000000
b1101010 $
0#
#535000000
b1101011 $
1#
#540000000
b1101100 $
0#
#545000000
b1101101 $
1#
#550000000
b1101110 $
0#
#555000000
b1101111 $
1#
#560000000
b1110000 $
0#
#565000000
b1110001 $
1#
#570000000
b1110010 $
0#
#575000000
b1110011 $
1#
#580000000
b1110100 $
0#
#585000000
b1110101 $
1#
#590000000
b1110110 $
0#
#595000000
b1110111 $
1#
#600000000
b1111000 $
0#
#605000000
b1111001 $
1#
#610000000
b1111010 $
0#
#615000000
b1111011 $
1#
#620000000
b1111100 $
0#
#625000000
b1111101 $
1#
#630000000
b1111110 $
0#
#635000000
b1111111 $
1#
#640000000
b10000000 $
0#
#645000000
b10000001 $
1#
#650000000
b10000010 $
0#
#655000000
b10000011 $
1#
#660000000
b10000100 $
0#
#665000000
b10000101 $
1#
#670000000
b10000110 $
0#
#675000000
b10000111 $
1#
#680000000
b10001000 $
0#
#685000000
b10001001 $
1#
#690000000
b10001010 $
0#
#695000000
b10001011 $
1#
#700000000
b10001100 $
0#
#705000000
b10001101 $
1#
#710000000
b10001110 $
0#
#715000000
b10001111 $
1#
#720000000
b10010000 $
0#
#725000000
b10010001 $
1#
#730000000
b10010010 $
0#
#735000000
b10010011 $
1#
#740000000
b10010100 $
0#
#745000000
b10010101 $
1#
#750000000
b10010110 $
0#
#755000000
b10010111 $
1#
#760000000
b10011000 $
0#
#765000000
b10011001 $
1#
#770000000
b10011010 $
0#
#775000000
b10011011 $
1#
#780000000
b10011100 $
0#
#785000000
b10011101 $
1#
#790000000
b10011110 $
0#
#795000000
b10011111 $
1#
#800000000
b10100000 $
0#
#805000000
b10100001 $
1#
#810000000
b10100010 $
0#
#815000000
b10100011 $
1#
#820000000
b10100100 $
0#
#825000000
b10100101 $
1#
#830000000
b10100110 $
0#
#835000000
b10100111 $
1#
#840000000
b10101000 $
0#
#845000000
b10101001 $
1#
#850000000
b10101010 $
0#
#855000000
b10101011 $
1#
#860000000
b10101100 $
0#
#865000000
b10101101 $
1#
#870000000
b10101110 $
0#
#875000000
b10101111 $
1#
#880000000
b10110000 $
0#
#885000000
b10110001 $
1#
#890000000
b10110010 $
0#
#895000000
b10110011 $
1#
#900000000
b10110100 $
0#
#905000000
b10110101 $
1#
#910000000
b10110110 $
0#
#915000000
b10110111 $
1#
#920000000
b10111000 $
0#
#925000000
b10111001 $
1#
#930000000
b10111010 $
0#
#935000000
b10111011 $
1#
#940000000
b10111100 $
0#
#945000000
b10111101 $
1#
#950000000
b10111110 $
0#
#955000000
b10111111 $
1#
#960000000
b11000000 $
0#
#965000000
b11000001 $
1#
#970000000
b11000010 $
0#
#975000000
b11000011 $
1#
#980000000
b11000100 $
0#
#985000000
b11000101 $
1#
#990000000
b11000110 $
0#
#995000000
b11000111 $
1#
#1000000000
b11001000 $
0#
#1005000000
b11001001 $
1#
#1010000000
b11001010 $
0#
#1015000000
b11001011 $
1#
#1020000000
b11001100 $
0#
#1025000000
b11001101 $
1#
#1030000000
b11001110 $
0#
#1035000000
b11001111 $
1#
#1040000000
b11010000 $
0#
#1045000000
b11010001 $
1#
#1050000000
b11010010 $
0#
#1055000000
b11010011 $
1#
#1060000000
b11010100 $
0#
#1065000000
b11010101 $
1#
#1070000000
b11010110 $
0#
#1075000000
b11010111 $
1#
#1080000000
b11011000 $
0#
#1085000000
b11011001 $
1#
#1090000000
b11011010 $
0#
#1095000000
b11011011 $
1#
#1100000000
b11011100 $
0#
#1105000000
b11011101 $
1#
#1110000000
b11011110 $
0#
#1115000000
b11011111 $
1#
#1120000000
b11100000 $
0#
#1125000000
b11100001 $
1#
#1130000000
b11100010 $
0#
#1135000000
b11100011 $
1#
#1140000000
b11100100 $
0#
#1145000000
b11100101 $
1#
#1150000000
b11100110 $
0#
#1155000000
b11100111 $
1#
#1160000000
b11101000 $
0#
#1165000000
b11101001 $
1#
#1170000000
b11101010 $
0#
#1175000000
b11101011 $
1#
#1180000000
b11101100 $
0#
#1185000000
b11101101 $
1#
#1190000000
b11101110 $
0#
#1195000000
b11101111 $
1#
#1200000000
b11110000 $
0#
#1205000000
b11110001 $
1#
#1210000000
b11110010 $
0#
#1215000000
b11110011 $
1#
#1220000000
b11110100 $
0#
#1225000000
b11110101 $
1#
#1230000000
b11110110 $
0#
#1235000000
b11110111 $
1#
#1240000000
b11111000 $
0#
#1245000000
b11111001 $
1#
#1250000000
b11111010 $
0#
#1255000000
b11111011 $
1#
#1260000000
b11111100 $
0#
#1265000000
b11111101 $
1#
#1270000000
b11111110 $
0#
#1275000000
b11111111 $
1#
#1280000000
b0 $
0#
#1285000000
b1 $
1#
#1290000000
b10 $
0#
#1295000000
b11 $
1#
#1300000000
b100 $
0#
#1305000000
b101 $
1#
#1310000000
b110 $
0#
#1315000000
b111 $
1#
#1320000000
b1000 $
0#
#1325000000
b1001 $
1#
#1330000000
1"
b1010 $
0#
#1335000000
b1 %
b1011 $
1#
#1340000000
b1100 $
0#
#1345000000
b10 %
b1101 $
1#
#1350000000
b1110 $
0#
#1355000000
b11 %
b1111 $
1#
#1360000000
b10000 $
0#
#1365000000
b100 %
b10001 $
1#
#1370000000
b10010 $
0#
#1375000000
1!
b101 %
b10011 $
1#
#1380000000
b10100 $
0#
#1385000000
b110 %
b10101 $
1#
#1390000000
b10110 $
0#
#1395000000
b111 %
b10111 $
1#
#1400000000
b11000 $
0#
#1405000000
b11001 $
1#
#1410000000
b11010 $
0#
#1415000000
b11011 $
1#
#1420000000
b11100 $
0#
#1425000000
b11101 $
1#
#1430000000
b11110 $
0#
#1435000000
b11111 $
1#
#1440000000
b100000 $
0#
#1445000000
b100001 $
1#
#1450000000
b100010 $
0#
#1455000000
b100011 $
1#
#1460000000
b100100 $
0#
#1465000000
b100101 $
1#
#1470000000
b100110 $
0#
#1475000000
b100111 $
1#
#1480000000
b101000 $
0#
#1485000000
b101001 $
1#
#1490000000
b101010 $
0#
#1495000000
b101011 $
1#
#1500000000
b101100 $
0#
#1505000000
b101101 $
1#
#1510000000
b101110 $
0#
#1515000000
b101111 $
1#
#1520000000
b110000 $
0#
#1525000000
b110001 $
1#
#1530000000
b110010 $
0#
#1535000000
b110011 $
1#
#1540000000
b110100 $
0#
#1545000000
b110101 $
1#
#1550000000
b110110 $
0#
#1555000000
b110111 $
1#
#1560000000
b111000 $
0#
#1565000000
b111001 $
1#
#1570000000
b111010 $
0#
#1575000000
b111011 $
1#
#1580000000
b111100 $
0#
#1585000000
b111101 $
1#
#1590000000
b111110 $
0#
#1595000000
b111111 $
1#
#1600000000
b1000000 $
0#
#1605000000
b1000001 $
1#
#1610000000
b1000010 $
0#
#1615000000
b1000011 $
1#
#1620000000
b1000100 $
0#
#1625000000
b1000101 $
1#
#1630000000
b1000110 $
0#
#1635000000
b1000111 $
1#
#1640000000
b1001000 $
0#
#1645000000
b1001001 $
1#
#1650000000
b1001010 $
0#
#1655000000
b1001011 $
1#
#1660000000
b1001100 $
0#
#1665000000
b1001101 $
1#
#1670000000
b1001110 $
0#
#1675000000
b1001111 $
1#
#1680000000
b1010000 $
0#
#1685000000
b1010001 $
1#
#1690000000
b1010010 $
0#
#1695000000
b1010011 $
1#
#1700000000
b1010100 $
0#
#1705000000
b1010101 $
1#
#1710000000
b1010110 $
0#
#1715000000
b1010111 $
1#
#1720000000
b1011000 $
0#
#1725000000
b1011001 $
1#
#1730000000
b1011010 $
0#
#1735000000
b1011011 $
1#
#1740000000
b1011100 $
0#
#1745000000
b1011101 $
1#
#1750000000
b1011110 $
0#
#1755000000
b1011111 $
1#
#1760000000
b1100000 $
0#
#1765000000
b1100001 $
1#
#1770000000
b1100010 $
0#
#1775000000
b1100011 $
1#
#1780000000
0"
b1100100 $
0#
#1785000000
0!
b0 %
b1100101 $
1#
#1790000000
b1100110 $
0#
#1795000000
b1100111 $
1#
#1800000000
b1101000 $
0#
#1805000000
b1101001 $
1#
#1810000000
b1101010 $
0#
#1815000000
b1101011 $
1#
#1820000000
b1101100 $
0#
#1825000000
b1101101 $
1#
#1830000000
b1101110 $
0#
#1835000000
b1101111 $
1#
#1840000000
b1110000 $
0#
#1845000000
b1110001 $
1#
#1850000000
b1110010 $
0#
#1855000000
b1110011 $
1#
#1860000000
b1110100 $
0#
#1865000000
b1110101 $
1#
#1870000000
b1110110 $
0#
#1875000000
b1110111 $
1#
#1880000000
b1111000 $
0#
#1885000000
b1111001 $
1#
#1890000000
b1111010 $
0#
#1895000000
b1111011 $
1#
#1900000000
b1111100 $
0#
#1905000000
b1111101 $
1#
#1910000000
b1111110 $
0#
#1915000000
b1111111 $
1#
#1920000000
b10000000 $
0#
#1925000000
b10000001 $
1#
#1930000000
b10000010 $
0#
#1935000000
b10000011 $
1#
#1940000000
b10000100 $
0#
#1945000000
b10000101 $
1#
#1950000000
b10000110 $
0#
#1955000000
b10000111 $
1#
#1960000000
b10001000 $
0#
#1965000000
b10001001 $
1#
#1970000000
b10001010 $
0#
#1975000000
b10001011 $
1#
#1980000000
b10001100 $
0#
#1985000000
b10001101 $
1#
#1990000000
b10001110 $
0#
#1995000000
b10001111 $
1#
#2000000000
b10010000 $
0#
#2005000000
b10010001 $
1#
#2010000000
b10010010 $
0#
#2015000000
b10010011 $
1#
#2020000000
b10010100 $
0#
#2025000000
b10010101 $
1#
#2030000000
b10010110 $
0#
#2035000000
b10010111 $
1#
#2040000000
b10011000 $
0#
#2045000000
b10011001 $
1#
#2050000000
b10011010 $
0#
#2055000000
b10011011 $
1#
#2060000000
b10011100 $
0#
#2065000000
b10011101 $
1#
#2070000000
b10011110 $
0#
#2075000000
b10011111 $
1#
#2080000000
b10100000 $
0#
#2085000000
b10100001 $
1#
#2090000000
b10100010 $
0#
#2095000000
b10100011 $
1#
#2100000000
b10100100 $
0#
#2105000000
b10100101 $
1#
#2110000000
b10100110 $
0#
#2115000000
b10100111 $
1#
#2120000000
b10101000 $
0#
#2125000000
b10101001 $
1#
#2130000000
b10101010 $
0#
#2135000000
b10101011 $
1#
#2140000000
b10101100 $
0#
#2145000000
b10101101 $
1#
#2150000000
b10101110 $
0#
#2155000000
b10101111 $
1#
#2160000000
b10110000 $
0#
#2165000000
b10110001 $
1#
#2170000000
b10110010 $
0#
#2175000000
b10110011 $
1#
#2180000000
b10110100 $
0#
#2185000000
b10110101 $
1#
#2190000000
b10110110 $
0#
#2195000000
b10110111 $
1#
#2200000000
b10111000 $
0#
#2205000000
b10111001 $
1#
#2210000000
b10111010 $
0#
#2215000000
b10111011 $
1#
#2220000000
b10111100 $
0#
#2225000000
b10111101 $
1#
#2230000000
b10111110 $
0#
#2235000000
b10111111 $
1#
#2240000000
b11000000 $
0#
#2245000000
b11000001 $
1#
#2250000000
b11000010 $
0#
#2255000000
b11000011 $
1#
#2260000000
b11000100 $
0#
#2265000000
b11000101 $
1#
#2270000000
b11000110 $
0#
#2275000000
b11000111 $
1#
#2280000000
b11001000 $
0#
#2285000000
b11001001 $
1#
#2290000000
b11001010 $
0#
#2295000000
b11001011 $
1#
#2300000000
b11001100 $
0#
#2305000000
b11001101 $
1#
#2310000000
b11001110 $
0#
#2315000000
b11001111 $
1#
#2320000000
b11010000 $
0#
#2325000000
b11010001 $
1#
#2330000000
b11010010 $
0#
#2335000000
b11010011 $
1#
#2340000000
b11010100 $
0#
#2345000000
b11010101 $
1#
#2350000000
b11010110 $
0#
#2355000000
b11010111 $
1#
#2360000000
b11011000 $
0#
#2365000000
b11011001 $
1#
#2370000000
b11011010 $
0#
#2375000000
b11011011 $
1#
#2380000000
b11011100 $
0#
#2385000000
b11011101 $
1#
#2390000000
b11011110 $
0#
#2395000000
b11011111 $
1#
#2400000000
b11100000 $
0#
#2405000000
b11100001 $
1#
#2410000000
b11100010 $
0#
#2415000000
b11100011 $
1#
#2420000000
b11100100 $
0#
#2425000000
b11100101 $
1#
#2430000000
b11100110 $
0#
#2435000000
b11100111 $
1#
#2440000000
b11101000 $
0#
#2445000000
b11101001 $
1#
#2450000000
b11101010 $
0#
#2455000000
b11101011 $
1#
#2460000000
b11101100 $
0#
#2465000000
b11101101 $
1#
#2470000000
b11101110 $
0#
#2475000000
b11101111 $
1#
#2480000000
b11110000 $
0#
#2485000000
b11110001 $
1#
#2490000000
b11110010 $
0#
#2495000000
b11110011 $
1#
#2500000000
b11110100 $
0#
