microwave_controller/timer_input_control/mux_2x1.v
module mux_2x1(
    input i0, i1, select,
    output F
);

    assign F = (i0 & ~select) || (i1 & select);

endmodule

microwave_controller/timer_input_control/testbenchs/mux_2x1_tb.v
`timescale 1ns/1ps
`include "..\mux_2x1.v"

module mux_2x1_tb;

    reg i0_tb, i1_tb, sel_tb;
    wire f_tb;

    mux_2x1 uut(i0_tb, i1_tb, sel_tb, f_tb);

    initial begin
        $dumpfile("../wave_forms/mux_2x1.vcd");
        $dumpvars(0, mux_2x1_tb);

        sel_tb = 0;

        i0_tb = 0; i1_tb = 0; #10;
        i0_tb = 0; i1_tb = 1; #10;
        i0_tb = 1; i1_tb = 0; #10;
        i0_tb = 1; i1_tb = 1; #10;

        sel_tb = 1;

        i0_tb = 0; i1_tb = 0; #10;
        i0_tb = 0; i1_tb = 1; #10;
        i0_tb = 1; i1_tb = 0; #10;
        i0_tb = 1; i1_tb = 1; #10;
    end

endmodule

microwave_controller/timer_input_control/wave_forms/mux_2x1.vcd
$date
	Sun May 01 18:02:20 2022
$end
$version
	Icarus Verilog
$end
$timescale
	1ps
$end
$scope module mux_2x1_tb $end
$var wire 1 ! f_tb $end
$var reg 1 " i0_tb $end
$var reg 1 # i1_tb $end
$var reg 1 $ sel_tb $end
$scope module uut $end
$var wire 1 ! F $end
$var wire 1 " i0 $end
$var wire 1 # i1 $end
$var wire 1 $ select $end
$upscope $end
$upscope $end
$enddefinitions $end
#0
$dumpvars
0$
0#
0"
0!
$end
#10000
1#
#20000
1!
0#
1"
#30000
1#
#40000
0!
0#
0"
1$
#50000
1!
1#
#60000
0!
0#
1"
#70000
1!
1#
