microwave_controller/timer_input_control/priority_encoder.v
module priority_encoder(
    keypad, enable_n,
    BCD_out, data_valid
);

    input wire [9:0] keypad;
    input wire enable_n;

    output reg [3:0] BCD_out;
    output wire data_valid;

    assign data_valid = ~enable_n && (keypad != 10'b00_0000_0000);

    always @(keypad, enable_n) begin
        if (~enable_n) begin
            if (keypad[9])
                BCD_out = 4'b1001;
            else if (keypad[8])
                BCD_out = 4'b1000;
            else if (keypad[7])
                BCD_out = 4'b0111;
            else if (keypad[6])
                BCD_out = 4'b0110;
            else if (keypad[5])
                BCD_out = 4'b0101;
            else if (keypad[4])
                BCD_out = 4'b0100;
            else if (keypad[3])
                BCD_out = 4'b0011;
            else if (keypad[2])
                BCD_out = 4'b0010;
            else if (keypad[1])
                BCD_out = 4'b0001;
            else if (keypad[0])
                BCD_out = 4'b0000;
            else
                BCD_out = 4'bxxxx;
        end
        else begin
            BCD_out = 4'bzzzz;
        end
    end

endmodule

microwave_controller/timer_input_control/testbenchs/priority_encoder_tb.v
`timescale 1ns/1ps
`include "..\priority_encoder.v"

module priority_encoder_tb;

    reg [9:0] keypad_tb;
    reg enable_n_tb;

    wire [3:0] BCD_out_tb;
    wire data_valid_tb;

    priority_encoder uut(.keypad(keypad_tb), .enable_n(enable_n_tb), .BCD_out(BCD_out_tb), .data_valid(data_valid_tb));

    initial begin
        $dumpfile("../wave_forms/priority_encoder.vcd");
        $dumpvars(0, priority_encoder_tb);

        enable_n_tb = 1;

        #10 keypad_tb = 10'b00_0000_0000;
        #10 keypad_tb = 10'b10_0101_0101;
        #10 keypad_tb = 10'b00_0000_0000;
        #10 keypad_tb = 10'b01_0110_1010;
        #10 keypad_tb = 10'b00_0000_0111;

        #10 enable_n_tb = 0;

        #10 keypad_tb = 10'b10_0101_0101;
        #10 keypad_tb = 10'b01_0110_1010;
        #10 keypad_tb = 10'b00_0000_0000;
        #10 keypad_tb = 10'b00_0000_0111;
        #10 keypad_tb = 10'b00_0000_0000; #10;
    end

endmodule

microwave_controller/timer_input_control/wave_forms/priority_encoder.vcd
$date
	Wed Apr 27 16:30:46 2022
$end
$version
	Icarus Verilog
$end
$timescale
	1ps
$end
$scope module priority_encoder_tb $end
$var wire 1 ! data_valid_tb $end
$var wire 4 " BCD_out_tb [3:0] $end
$var reg 1 # enable_n_tb $end
$var reg 10 $ keypad_tb [9:0] $end
$scope module uut $end
$var wire 1 ! data_valid $end
$var wire 1 # enable_n $end
$var wire 10 % keypad [9:0] $end
$var reg 4 & BCD_out [3:0] $end
$upscope $end
$upscope $end
$enddefinitions $end
#0
$dumpvars
bz &
bx %
bx $
1#
bz "
0!
$end
#10000
b0 $
b0 %
#20000
b1001010101 $
b1001010101 %
#30000
b0 $
b0 %
#40000
b101101010 $
b101101010 %
#50000
b111 $
b111 %
#60000
1!
b10 "
b10 &
0#
#70000
b1001 "
b1001 &
b1001010101 $
b1001010101 %
#80000
b1000 "
b1000 &
b101101010 $
b101101010 %
#90000
bx "
bx &
0!
b0 $
b0 %
#100000
b10 "
b10 &
1!
b111 $
b111 %
#110000
bx "
bx &
0!
b0 $
b0 %
