microwave_controller/timer_input_control/mux_2x1.v
module mux_2x1(
    input i0, i1, select,
    output F
);

    assign F = (i0 & ~select) || (i1 & select);

endmodule

microwave_controller/timer_input_control/debounce_delay.v
module debounce_delay(
    clock, clear,
    edge_out
);

    input clock, clear;
    output reg edge_out;

    reg [2:0] count;

    initial begin
        count <= 3'd7;
        edge_out <= 1'b0;
    end

    always @(posedge clock) begin
        if (clear == 1'b0) begin
            count <= 3'd0;
            edge_out <= 1'b0;
        end else begin
            if (count < 3'd7) begin
                count <= count + 3'd1;
            end else begin
                count <= 3'd7;
            end

            if (count == 3'd4) begin
                edge_out <= 1'b1;
            end
        end
    end

endmodule

microwave_controller/timer_input_control/frequency_divide_by_100.v
module frequency_divide_by_100 (
    input in_clock,
    output reg out_clock
);

    reg [6:0] count;

    initial begin
        count <= 7'd0;
        out_clock = 1'b0;
    end

    always @(posedge in_clock) begin
        count <= count + 7'd1;

        if (count >= 7'd99) begin
            count <= 7'd0;
        end

        if (count < 7'd50) begin
            out_clock <= 1'b1;
        end else begin
            out_clock <= 1'b0;
        end
    end

endmodule

microwave_controller/timer_input_control/priority_encoder.v
module priority_encoder(
    keypad, enable_n,
    BCD_out, data_valid
);

    input wire [9:0] keypad;
    input wire enable_n;

    output reg [3:0] BCD_out;
    output wire data_valid;

    assign data_valid = ~enable_n && (keypad != 10'b00_0000_0000);

    always @(keypad, enable_n) begin
        if (~enable_n) begin
            if (keypad[9])
                BCD_out = 4'b1001;
            else if (keypad[8])
                BCD_out = 4'b1000;
            else if (keypad[7])
                BCD_out = 4'b0111;
            else if (keypad[6])
                BCD_out = 4'b0110;
            else if (keypad[5])
                BCD_out = 4'b0101;
            else if (keypad[4])
                BCD_out = 4'b0100;
            else if (keypad[3])
                BCD_out = 4'b0011;
            else if (keypad[2])
                BCD_out = 4'b0010;
            else if (keypad[1])
                BCD_out = 4'b0001;
            else if (keypad[0])
                BCD_out = 4'b0000;
            else
                BCD_out = 4'bxxxx;
        end
        else begin
            BCD_out = 4'bzzzz;
        end
    end

endmodule

microwave_controller/timer_input_control/timer_control_level2.v
`include "priority_encoder.v"
`include "frequency_divide_by_100.v"
`include "debounce_delay.v"
`include "mux_2x1.v"

module timer_control_level2(
    keypad, enable_n, clock_100Hz,
    D, load_n, pgt_1Hz
);

    input [9:0] keypad;
    input enable_n, clock_100Hz;
    
    output wire [3:0] D;
    output wire load_n, pgt_1Hz;

    wire clock_1Hz, data_valid, delayed_data_valid;

    priority_encoder encoder(.keypad(keypad), .enable_n(enable_n), .BCD_out(D), .data_valid(data_valid));

    frequency_divide_by_100 divide(.in_clock(clock_100Hz), .out_clock(clock_1Hz));

    debounce_delay delay(.clock(clock_100Hz), .clear(data_valid), .edge_out(delayed_data_valid));

    mux_2x1 mux(.i0(delayed_data_valid), .i1(clock_1Hz), .select(enable_n), .F(pgt_1Hz));

    assign load_n = ~data_valid;

endmodule

microwave_controller/timer_input_control/testbenchs/timer_control_level2_tb.v
`timescale 1ms/1ns
`include "timer_control_level2.v"

module timer_control_level2_tb;

    reg [9:0] keypad_tb;
    reg enable_n_tb, clock_100Hz_tb;

    wire [3:0] D_tb;
    wire load_n_tb, pgt_1Hz_tb;

    timer_control_level2 uut(keypad_tb, enable_n_tb, clock_100Hz_tb, D_tb, load_n_tb, pgt_1Hz_tb);

    initial begin
        $dumpfile("./wave_forms/timer_control_level2.vcd");
        $dumpvars(0, timer_control_level2_tb);

        clock_100Hz_tb = 0; enable_n_tb = 1; keypad_tb = 10'b00_0000_0000;
    end

    initial begin
        repeat(500)
            #5 clock_100Hz_tb = ~clock_100Hz_tb;
    end 

    initial begin
        #10 keypad_tb = 10'b00_0001_0000;
        #100 keypad_tb = 10'b00_0000_0000;
        #100 keypad_tb = 10'b00_1000_0000;
        #300 keypad_tb = 10'b10_0010_0001;
        #100 keypad_tb = 10'b00_0000_0000;

        #10 enable_n_tb = 0;

        #10 keypad_tb = 10'b00_1001_0000;
        #100 keypad_tb = 10'b00_0000_0000;
        #100 keypad_tb = 10'b00_0010_0000;
        #300 keypad_tb = 10'b01_0010_0001;
        #100 keypad_tb = 10'b00_0000_0000;
        #100 keypad_tb = 10'b00_1100_0000;
        #100 keypad_tb = 10'b00_0000_0000;
        
        #10 enable_n_tb = 1; #100;
    end

endmodule

microwave_controller/timer_input_control/wave_forms/timer_control_level2.vcd
$date
	Sun May 01 19:26:19 2022
$end
$version
	Icarus Verilog
$end
$timescale
	1ns
$end
$scope module timer_control_level2_tb $end
$var wire 1 ! pgt_1Hz_tb $end
$var wire 1 " load_n_tb $end
$var wire 4 # D_tb [3:0] $end
$var reg 1 $ clock_100Hz_tb $end
$var reg 1 % enable_n_tb $end
$var reg 10 & keypad_tb [9:0] $end
$scope module uut $end
$var wire 1 $ clock_100Hz $end
$var wire 1 % enable_n $end
$var wire 10 ' keypad [9:0] $end
$var wire 1 " load_n $end
$var wire 1 ! pgt_1Hz $end
$var wire 1 ( delayed_data_valid $end
$var wire 1 ) data_valid $end
$var wire 1 * clock_1Hz $end
$var wire 4 + D [3:0] $end
$scope module delay $end
$var wire 1 $ clock $end
$var wire 1 ) clear $end
$var reg 3 , count [2:0] $end
$var reg 1 ( edge_out $end
$upscope $end
$scope module divide $end
$var wire 1 $ in_clock $end
$var reg 7 - count [6:0] $end
$var reg 1 * out_clock $end
$upscope $end
$scope module encoder $end
$var wire 1 ) data_valid $end
$var wire 1 % enable_n $end
$var wire 10 . keypad [9:0] $end
$var reg 4 / BCD_out [3:0] $end
$upscope $end
$scope module mux $end
$var wire 1 ! F $end
$var wire 1 ( i0 $end
$var wire 1 * i1 $end
$var wire 1 % select $end
$upscope $end
$upscope $end
$upscope $end
$enddefinitions $end
#0
$dumpvars
bz /
b0 .
b0 -
b111 ,
bz +
0*
0)
0(
b0 '
b0 &
1%
0$
bz #
1"
0!
$end
#5000000
1!
1*
b1 -
b0 ,
1$
#10000000
0$
b10000 &
b10000 '
b10000 .
#15000000
b10 -
1$
#20000000
0$
#25000000
b11 -
1$
#30000000
0$
#35000000
b100 -
1$
#40000000
0$
#45000000
b101 -
1$
#50000000
0$
#55000000
b110 -
1$
#60000000
0$
#65000000
b111 -
1$
#70000000
0$
#75000000
b1000 -
1$
#80000000
0$
#85000000
b1001 -
1$
#90000000
0$
#95000000
b1010 -
1$
#100000000
0$
#105000000
b1011 -
1$
#110000000
0$
b0 &
b0 '
b0 .
#115000000
b1100 -
1$
#120000000
0$
#125000000
b1101 -
1$
#130000000
0$
#135000000
b1110 -
1$
#140000000
0$
#145000000
b1111 -
1$
#150000000
0$
#155000000
b10000 -
1$
#160000000
0$
#165000000
b10001 -
1$
#170000000
0$
#175000000
b10010 -
1$
#180000000
0$
#185000000
b10011 -
1$
#190000000
0$
#195000000
b10100 -
1$
#200000000
0$
#205000000
b10101 -
1$
#210000000
0$
b10000000 &
b10000000 '
b10000000 .
#215000000
b10110 -
1$
#220000000
0$
#225000000
b10111 -
1$
#230000000
0$
#235000000
b11000 -
1$
#240000000
0$
#245000000
b11001 -
1$
#250000000
0$
#255000000
b11010 -
1$
#260000000
0$
#265000000
b11011 -
1$
#270000000
0$
#275000000
b11100 -
1$
#280000000
0$
#285000000
b11101 -
1$
#290000000
0$
#295000000
b11110 -
1$
#300000000
0$
#305000000
b11111 -
1$
#310000000
0$
#315000000
b100000 -
1$
#320000000
0$
#325000000
b100001 -
1$
#330000000
0$
#335000000
b100010 -
1$
#340000000
0$
#345000000
b100011 -
1$
#350000000
0$
#355000000
b100100 -
1$
#360000000
0$
#365000000
b100101 -
1$
#370000000
0$
#375000000
b100110 -
1$
#380000000
0$
#385000000
b100111 -
1$
#390000000
0$
#395000000
b101000 -
1$
#400000000
0$
#405000000
b101001 -
1$
#410000000
0$
#415000000
b101010 -
1$
#420000000
0$
#425000000
b101011 -
1$
#430000000
0$
#435000000
b101100 -
1$
#440000000
0$
#445000000
b101101 -
1$
#450000000
0$
#455000000
b101110 -
1$
#460000000
0$
#465000000
b101111 -
1$
#470000000
0$
#475000000
b110000 -
1$
#480000000
0$
#485000000
b110001 -
1$
#490000000
0$
#495000000
b110010 -
1$
#500000000
0$
#505000000
0!
0*
b110011 -
1$
#510000000
0$
b1000100001 &
b1000100001 '
b1000100001 .
#515000000
b110100 -
1$
#520000000
0$
#525000000
b110101 -
1$
#530000000
0$
#535000000
b110110 -
1$
#540000000
0$
#545000000
b110111 -
1$
#550000000
0$
#555000000
b111000 -
1$
#560000000
0$
#565000000
b111001 -
1$
#570000000
0$
#575000000
b111010 -
1$
#580000000
0$
#585000000
b111011 -
1$
#590000000
0$
#595000000
b111100 -
1$
#600000000
0$
#605000000
b111101 -
1$
#610000000
0$
b0 &
b0 '
b0 .
#615000000
b111110 -
1$
#620000000
bx #
bx +
bx /
0$
0%
#625000000
b111111 -
1$
#630000000
0"
b111 #
b111 +
b111 /
1)
0$
b10010000 &
b10010000 '
b10010000 .
#635000000
b1 ,
b1000000 -
1$
#640000000
0$
#645000000
b1000001 -
b10 ,
1$
#650000000
0$
#655000000
b11 ,
b1000010 -
1$
#660000000
0$
#665000000
b1000011 -
b100 ,
1$
#670000000
0$
#675000000
1!
1(
b101 ,
b1000100 -
1$
#680000000
0$
#685000000
b1000101 -
b110 ,
1$
#690000000
0$
#695000000
b111 ,
b1000110 -
1$
#700000000
0$
#705000000
b1000111 -
1$
#710000000
0$
#715000000
b1001000 -
1$
#720000000
0$
#725000000
b1001001 -
1$
#730000000
1"
bx #
bx +
bx /
0)
0$
b0 &
b0 '
b0 .
#735000000
0!
0(
b0 ,
b1001010 -
1$
#740000000
0$
#745000000
b1001011 -
1$
#750000000
0$
#755000000
b1001100 -
1$
#760000000
0$
#765000000
b1001101 -
1$
#770000000
0$
#775000000
b1001110 -
1$
#780000000
0$
#785000000
b1001111 -
1$
#790000000
0$
#795000000
b1010000 -
1$
#800000000
0$
#805000000
b1010001 -
1$
#810000000
0$
#815000000
b1010010 -
1$
#820000000
0$
#825000000
b1010011 -
1$
#830000000
0"
b101 #
b101 +
b101 /
1)
0$
b100000 &
b100000 '
b100000 .
#835000000
b1 ,
b1010100 -
1$
#840000000
0$
#845000000
b1010101 -
b10 ,
1$
#850000000
0$
#855000000
b11 ,
b1010110 -
1$
#860000000
0$
#865000000
b1010111 -
b100 ,
1$
#870000000
0$
#875000000
1!
1(
b101 ,
b1011000 -
1$
#880000000
0$
#885000000
b1011001 -
b110 ,
1$
#890000000
0$
#895000000
b111 ,
b1011010 -
1$
#900000000
0$
#905000000
b1011011 -
1$
#910000000
0$
#915000000
b1011100 -
1$
#920000000
0$
#925000000
b1011101 -
1$
#930000000
0$
#935000000
b1011110 -
1$
#940000000
0$
#945000000
b1011111 -
1$
#950000000
0$
#955000000
b1100000 -
1$
#960000000
0$
#965000000
b1100001 -
1$
#970000000
0$
#975000000
b1100010 -
1$
#980000000
0$
#985000000
b1100011 -
1$
#990000000
0$
#995000000
b0 -
1$
#1000000000
0$
#1005000000
1*
b1 -
1$
#1010000000
0$
#1015000000
b10 -
1$
#1020000000
0$
#1025000000
b11 -
1$
#1030000000
0$
#1035000000
b100 -
1$
#1040000000
0$
#1045000000
b101 -
1$
#1050000000
0$
#1055000000
b110 -
1$
#1060000000
0$
#1065000000
b111 -
1$
#1070000000
0$
#1075000000
b1000 -
1$
#1080000000
0$
#1085000000
b1001 -
1$
#1090000000
0$
#1095000000
b1010 -
1$
#1100000000
0$
#1105000000
b1011 -
1$
#1110000000
0$
#1115000000
b1100 -
1$
#1120000000
0$
#1125000000
b1101 -
1$
#1130000000
b1000 #
b1000 +
b1000 /
0$
b100100001 &
b100100001 '
b100100001 .
#1135000000
b1110 -
1$
#1140000000
0$
#1145000000
b1111 -
1$
#1150000000
0$
#1155000000
b10000 -
1$
#1160000000
0$
#1165000000
b10001 -
1$
#1170000000
0$
#1175000000
b10010 -
1$
#1180000000
0$
#1185000000
b10011 -
1$
#1190000000
0$
#1195000000
b10100 -
1$
#1200000000
0$
#1205000000
b10101 -
1$
#1210000000
0$
#1215000000
b10110 -
1$
#1220000000
0$
#1225000000
b10111 -
1$
#1230000000
1"
bx #
bx +
bx /
0)
0$
b0 &
b0 '
b0 .
#1235000000
0!
0(
b0 ,
b11000 -
1$
#1240000000
0$
#1245000000
b11001 -
1$
#1250000000
0$
#1255000000
b11010 -
1$
#1260000000
0$
#1265000000
b11011 -
1$
#1270000000
0$
#1275000000
b11100 -
1$
#1280000000
0$
#1285000000
b11101 -
1$
#1290000000
0$
#1295000000
b11110 -
1$
#1300000000
0$
#1305000000
b11111 -
1$
#1310000000
0$
#1315000000
b100000 -
1$
#1320000000
0$
#1325000000
b100001 -
1$
#1330000000
0"
b111 #
b111 +
b111 /
1)
0$
b11000000 &
b11000000 '
b11000000 .
#1335000000
b1 ,
b100010 -
1$
#1340000000
0$
#1345000000
b100011 -
b10 ,
1$
#1350000000
0$
#1355000000
b11 ,
b100100 -
1$
#1360000000
0$
#1365000000
b100101 -
b100 ,
1$
#1370000000
0$
#1375000000
1!
1(
b101 ,
b100110 -
1$
#1380000000
0$
#1385000000
b100111 -
b110 ,
1$
#1390000000
0$
#1395000000
b111 ,
b101000 -
1$
#1400000000
0$
#1405000000
b101001 -
1$
#1410000000
0$
#1415000000
b101010 -
1$
#1420000000
0$
#1425000000
b101011 -
1$
#1430000000
1"
bx #
bx +
bx /
0)
0$
b0 &
b0 '
b0 .
#1435000000
0!
0(
b0 ,
b101100 -
1$
#1440000000
1!
bz #
bz +
bz /
0$
1%
#1445000000
b101101 -
1$
#1450000000
0$
#1455000000
b101110 -
1$
#1460000000
0$
#1465000000
b101111 -
1$
#1470000000
0$
#1475000000
b110000 -
1$
#1480000000
0$
#1485000000
b110001 -
1$
#1490000000
0$
#1495000000
b110010 -
1$
#1500000000
0$
#1505000000
0!
0*
b110011 -
1$
#1510000000
0$
#1515000000
b110100 -
1$
#1520000000
0$
#1525000000
b110101 -
1$
#1530000000
0$
#1535000000
b110110 -
1$
#1540000000
0$
#1545000000
b110111 -
1$
#1550000000
0$
#1555000000
b111000 -
1$
#1560000000
0$
#1565000000
b111001 -
1$
#1570000000
0$
#1575000000
b111010 -
1$
#1580000000
0$
#1585000000
b111011 -
1$
#1590000000
0$
#1595000000
b111100 -
1$
#1600000000
0$
#1605000000
b111101 -
1$
#1610000000
0$
#1615000000
b111110 -
1$
#1620000000
0$
#1625000000
b111111 -
1$
#1630000000
0$
#1635000000
b1000000 -
1$
#1640000000
0$
#1645000000
b1000001 -
1$
#1650000000
0$
#1655000000
b1000010 -
1$
#1660000000
0$
#1665000000
b1000011 -
1$
#1670000000
0$
#1675000000
b1000100 -
1$
#1680000000
0$
#1685000000
b1000101 -
1$
#1690000000
0$
#1695000000
b1000110 -
1$
#1700000000
0$
#1705000000
b1000111 -
1$
#1710000000
0$
#1715000000
b1001000 -
1$
#1720000000
0$
#1725000000
b1001001 -
1$
#1730000000
0$
#1735000000
b1001010 -
1$
#1740000000
0$
#1745000000
b1001011 -
1$
#1750000000
0$
#1755000000
b1001100 -
1$
#1760000000
0$
#1765000000
b1001101 -
1$
#1770000000
0$
#1775000000
b1001110 -
1$
#1780000000
0$
#1785000000
b1001111 -
1$
#1790000000
0$
#1795000000
b1010000 -
1$
#1800000000
0$
#1805000000
b1010001 -
1$
#1810000000
0$
#1815000000
b1010010 -
1$
#1820000000
0$
#1825000000
b1010011 -
1$
#1830000000
0$
#1835000000
b1010100 -
1$
#1840000000
0$
#1845000000
b1010101 -
1$
#1850000000
0$
#1855000000
b1010110 -
1$
#1860000000
0$
#1865000000
b1010111 -
1$
#1870000000
0$
#1875000000
b1011000 -
1$
#1880000000
0$
#1885000000
b1011001 -
1$
#1890000000
0$
#1895000000
b1011010 -
1$
#1900000000
0$
#1905000000
b1011011 -
1$
#1910000000
0$
#1915000000
b1011100 -
1$
#1920000000
0$
#1925000000
b1011101 -
1$
#1930000000
0$
#1935000000
b1011110 -
1$
#1940000000
0$
#1945000000
b1011111 -
1$
#1950000000
0$
#1955000000
b1100000 -
1$
#1960000000
0$
#1965000000
b1100001 -
1$
#1970000000
0$
#1975000000
b1100010 -
1$
#1980000000
0$
#1985000000
b1100011 -
1$
#1990000000
0$
#1995000000
b0 -
1$
#2000000000
0$
#2005000000
1!
1*
b1 -
1$
#2010000000
0$
#2015000000
b10 -
1$
#2020000000
0$
#2025000000
b11 -
1$
#2030000000
0$
#2035000000
b100 -
1$
#2040000000
0$
#2045000000
b101 -
1$
#2050000000
0$
#2055000000
b110 -
1$
#2060000000
0$
#2065000000
b111 -
1$
#2070000000
0$
#2075000000
b1000 -
1$
#2080000000
0$
#2085000000
b1001 -
1$
#2090000000
0$
#2095000000
b1010 -
1$
#2100000000
0$
#2105000000
b1011 -
1$
#2110000000
0$
#2115000000
b1100 -
1$
#2120000000
0$
#2125000000
b1101 -
1$
#2130000000
0$
#2135000000
b1110 -
1$
#2140000000
0$
#2145000000
b1111 -
1$
#2150000000
0$
#2155000000
b10000 -
1$
#2160000000
0$
#2165000000
b10001 -
1$
#2170000000
0$
#2175000000
b10010 -
1$
#2180000000
0$
#2185000000
b10011 -
1$
#2190000000
0$
#2195000000
b10100 -
1$
#2200000000
0$
#2205000000
b10101 -
1$
#2210000000
0$
#2215000000
b10110 -
1$
#2220000000
0$
#2225000000
b10111 -
1$
#2230000000
0$
#2235000000
b11000 -
1$
#2240000000
0$
#2245000000
b11001 -
1$
#2250000000
0$
#2255000000
b11010 -
1$
#2260000000
0$
#2265000000
b11011 -
1$
#2270000000
0$
#2275000000
b11100 -
1$
#2280000000
0$
#2285000000
b11101 -
1$
#2290000000
0$
#2295000000
b11110 -
1$
#2300000000
0$
#2305000000
b11111 -
1$
#2310000000
0$
#2315000000
b100000 -
1$
#2320000000
0$
#2325000000
b100001 -
1$
#2330000000
0$
#2335000000
b100010 -
1$
#2340000000
0$
#2345000000
b100011 -
1$
#2350000000
0$
#2355000000
b100100 -
1$
#2360000000
0$
#2365000000
b100101 -
1$
#2370000000
0$
#2375000000
b100110 -
1$
#2380000000
0$
#2385000000
b100111 -
1$
#2390000000
0$
#2395000000
b101000 -
1$
#2400000000
0$
#2405000000
b101001 -
1$
#2410000000
0$
#2415000000
b101010 -
1$
#2420000000
0$
#2425000000
b101011 -
1$
#2430000000
0$
#2435000000
b101100 -
1$
#2440000000
0$
#2445000000
b101101 -
1$
#2450000000
0$
#2455000000
b101110 -
1$
#2460000000
0$
#2465000000
b101111 -
1$
#2470000000
0$
#2475000000
b110000 -
1$
#2480000000
0$
#2485000000
b110001 -
1$
#2490000000
0$
#2495000000
b110010 -
1$
